{
  "minecraft:adventure/root": {
    "criteria": {
      "killed_something": "2023-08-30 00:15:42 +0800"
    },
    "done": true
  },
  "minecraft:adventure/kill_a_mob": {
    "criteria": {
      "slime": "2023-08-30 00:15:42 +0800"
    },
    "done": true
  },
  "minecraft:adventure/kill_all_mobs": {
    "criteria": {
      "slime": "2023-08-30 00:15:42 +0800"
    },
    "done": false
  },
  "minecraft:adventure/adventuring_time": {
    "criteria": {
      "plains": "2023-08-30 00:15:03 +0800"
    },
    "done": false
  }
}